structobj/__init__.py
structobj/structobj.py
structobj-0.0.1.dist-info/LICENSE
structobj-0.0.1.dist-info/METADATA
structobj-0.0.1.dist-info/WHEEL
structobj-0.0.1.dist-info/RECORD
