Metadata-Version: 2.1
Name: structobj
Version: 0.0.1
Summary: Conversion between data structures and object strutures
License: MIT
Author: flokapi
Author-email: flokapi@pm.me
Requires-Python: >=3.7,<4.0
Classifier: License :: OSI Approved :: MIT License
Classifier: Programming Language :: Python :: 3
Classifier: Programming Language :: Python :: 3.7
Classifier: Programming Language :: Python :: 3.8
Classifier: Programming Language :: Python :: 3.9
Classifier: Programming Language :: Python :: 3.10
Classifier: Programming Language :: Python :: 3.11
Requires-Dist: pytest (>=7.2.0,<8.0.0)
Project-URL: documentation, https://github.com/flokapi/structobj
Project-URL: homepage, https://github.com/flokapi/structobj
Project-URL: repository, https://github.com/flokapi/structobj
